MANIFEST.in
README.txt
setup.cfg
setup.py
zopeskel.txt
docs/HISTORY.txt
docs/INSTALL.txt
docs/LICENSE.txt
plonetheme/__init__.py
plonetheme.tidyblog.egg-info/PKG-INFO
plonetheme.tidyblog.egg-info/SOURCES.txt
plonetheme.tidyblog.egg-info/dependency_links.txt
plonetheme.tidyblog.egg-info/entry_points.txt
plonetheme.tidyblog.egg-info/namespace_packages.txt
plonetheme.tidyblog.egg-info/not-zip-safe
plonetheme.tidyblog.egg-info/requires.txt
plonetheme.tidyblog.egg-info/top_level.txt
plonetheme/tidyblog/README.txt
plonetheme/tidyblog/__init__.py
plonetheme/tidyblog/configure.zcml
plonetheme/tidyblog/profiles.zcml
plonetheme/tidyblog/skins.zcml
plonetheme/tidyblog/tests.py
plonetheme/tidyblog/version.txt
plonetheme/tidyblog/browser/__init__.py
plonetheme/tidyblog/browser/configure.zcml
plonetheme/tidyblog/browser/interfaces.py
plonetheme/tidyblog/browser/viewlet.pt
plonetheme/tidyblog/browser/viewlets.py
plonetheme/tidyblog/browser/images/README.txt
plonetheme/tidyblog/browser/stylesheets/README.txt
plonetheme/tidyblog/browser/stylesheets/main.css
plonetheme/tidyblog/profiles/default/cssregistry.xml
plonetheme/tidyblog/profiles/default/jsregistry.xml
plonetheme/tidyblog/profiles/default/metadata.xml
plonetheme/tidyblog/profiles/default/skins.xml
plonetheme/tidyblog/profiles/default/viewlets.xml
plonetheme/tidyblog/skins/plonetheme_tidyblog_custom_images/CONTENT.txt
plonetheme/tidyblog/skins/plonetheme_tidyblog_custom_images/arrow.gif
plonetheme/tidyblog/skins/plonetheme_tidyblog_custom_images/bg.gif
plonetheme/tidyblog/skins/plonetheme_tidyblog_custom_images/bg_calendar.gif
plonetheme/tidyblog/skins/plonetheme_tidyblog_custom_images/body_bg.gif
plonetheme/tidyblog/skins/plonetheme_tidyblog_custom_images/comment_corner.gif
plonetheme/tidyblog/skins/plonetheme_tidyblog_custom_images/comment_corner2.gif
plonetheme/tidyblog/skins/plonetheme_tidyblog_custom_images/comments.gif
plonetheme/tidyblog/skins/plonetheme_tidyblog_custom_images/email_link.gif
plonetheme/tidyblog/skins/plonetheme_tidyblog_custom_images/folder_heart.gif
plonetheme/tidyblog/skins/plonetheme_tidyblog_custom_images/footer_bg.gif
plonetheme/tidyblog/skins/plonetheme_tidyblog_custom_images/gallery_loading.gif
plonetheme/tidyblog/skins/plonetheme_tidyblog_custom_images/icon_area.gif
plonetheme/tidyblog/skins/plonetheme_tidyblog_custom_images/list_bg.gif
