Metadata-Version: 1.0
Name: plonetheme.tidyblog
Version: 1.2.1
Summary: An installable theme for Plone 3.0
Home-page: http://d9t.de
Author: Niels Steurer
Author-email: niels.steurer@d9t.de
License: GPL
Keywords: web zope plone theme
Platform: UNKNOWN
Classifier: Framework :: Plone
Classifier: Programming Language :: Python
Classifier: Topic :: Software Development :: Libraries :: Python Modules
